fastxs3d.cpython-313-darwin.so
xs3d/twod.py
xs3d/__init__.py
xs3d/typing.py
xs3d-1.13.0.dist-info/RECORD
xs3d-1.13.0.dist-info/WHEEL
xs3d-1.13.0.dist-info/pbr.json
xs3d-1.13.0.dist-info/top_level.txt
xs3d-1.13.0.dist-info/METADATA
xs3d-1.13.0.dist-info/licenses/LICENSE
xs3d-1.13.0.dist-info/licenses/AUTHORS
xs3d-1.13.0.dist-info/licenses/COPYING.LESSER
