Metadata-Version: 2.1
Name: xs3d
Version: 1.13.0
Summary: Compute cross sectional area of 3d shapes.
Home-page: https://github.com/seung-lab/cross-section/
Author: William Silversmith
Author-email: ws9@princeton.edu
License: "LGPL-3.0-or-later"
Classifier: Intended Audience :: Developers
Classifier: Development Status :: 4 - Beta
Classifier: Programming Language :: Python
Classifier: Programming Language :: Python :: 3
Classifier: Programming Language :: Python :: 3.9
Classifier: Programming Language :: Python :: 3.10
Classifier: Programming Language :: Python :: 3.11
Classifier: Programming Language :: Python :: 3.12
Classifier: Programming Language :: Python :: 3.13
Classifier: Topic :: Utilities
Classifier: Topic :: Scientific/Engineering :: Image Processing
License-File: LICENSE
License-File: COPYING.LESSER
